gwlearn/__init__.py
gwlearn/base.py
gwlearn/ensemble.py
gwlearn/linear_model.py
gwlearn/py.typed
gwlearn/search.py
gwlearn/undersample.py
gwlearn/tests/__init__.py
gwlearn/tests/conftest.py
gwlearn/tests/test_base.py
gwlearn/tests/test_ensemble.py
gwlearn/tests/test_linear_model.py
gwlearn/tests/test_search.py
gwlearn-0.1.1.dist-info/licenses/LICENSE
gwlearn-0.1.1.dist-info/METADATA
gwlearn-0.1.1.dist-info/WHEEL
gwlearn-0.1.1.dist-info/top_level.txt
gwlearn-0.1.1.dist-info/RECORD
