Metadata-Version: 2.4
Name: gwlearn
Version: 0.1.1
Summary: Geographically weighted modeling based on scikit-learn.
Author-email: Martin Fleischmann <martin@martinfleischmann.net>
License-Expression: BSD-3-Clause
Project-URL: Homepage, https://pysal.org/gwlearn/
Project-URL: Documentation, https://pysal.org/gwlearn/
Project-URL: Repository, https://github.com/pysal/gwlearn.git
Project-URL: Issues, https://github.com/pysal/gwlearn/issues
Project-URL: Changelog, https://github.com/pysal/gwlearn/releases
Classifier: Programming Language :: Python :: 3
Classifier: Operating System :: OS Independent
Classifier: Intended Audience :: Science/Research
Classifier: Topic :: Scientific/Engineering :: GIS
Requires-Python: >=3.11
License-File: LICENSE
Requires-Dist: geopandas>=1.0.0
Requires-Dist: joblib>=1.4.0
Requires-Dist: libpysal>=4.12
Requires-Dist: numpy>=1.26.0
Requires-Dist: scipy>=1.12.0
Requires-Dist: scikit-learn>=1.4.0
Requires-Dist: pandas>=2.1.0
Dynamic: license-file
